my_countries_api_12345/__init__.py
my_countries_api_12345/api_helper.py
my_countries_api_12345/configuration.py
my_countries_api_12345/decorators.py
my_countries_api_12345/my_countries_api_12345_client.py
my_countries_api_12345/controllers/__init__.py
my_countries_api_12345/controllers/base_controller.py
my_countries_api_12345/controllers/countries_controller.py
my_countries_api_12345/exceptions/__init__.py
my_countries_api_12345/exceptions/api_exception.py
my_countries_api_12345/http/__init__.py
my_countries_api_12345/http/http_call_back.py
my_countries_api_12345/http/http_client.py
my_countries_api_12345/http/http_context.py
my_countries_api_12345/http/http_method_enum.py
my_countries_api_12345/http/http_request.py
my_countries_api_12345/http/http_response.py
my_countries_api_12345/http/requests_client.py
my_countries_api_12345/models/__init__.py
my_countries_api_12345/models/country_info.py
my_countries_api_12345/models/country_response.py
tests/__init__.py
tests/http_response_catcher.py
tests/test_helper.py
tests/controllers/__init__.py
tests/controllers/controller_test_base.py
tests/controllers/test_countries_controller.py
My_CountriesAPI_12345-1.0.dist-info/LICENSE
My_CountriesAPI_12345-1.0.dist-info/METADATA
My_CountriesAPI_12345-1.0.dist-info/WHEEL
My_CountriesAPI_12345-1.0.dist-info/top_level.txt
My_CountriesAPI_12345-1.0.dist-info/RECORD
